cnpd/__init__.py
cnpd/example.py
python_cnpd-0.1.0.dist-info/licenses/LICENSE
python_cnpd-0.1.0.dist-info/METADATA
python_cnpd-0.1.0.dist-info/WHEEL
python_cnpd-0.1.0.dist-info/top_level.txt
python_cnpd-0.1.0.dist-info/RECORD
